pyosmo/__init__.py
pyosmo/config.py
pyosmo/decorators.py
pyosmo/main.py
pyosmo/model.py
pyosmo/osmo.py
pyosmo/algorithm/__init__.py
pyosmo/algorithm/balancing.py
pyosmo/algorithm/base.py
pyosmo/algorithm/random.py
pyosmo/algorithm/weighted.py
pyosmo/end_conditions/__init__.py
pyosmo/end_conditions/base.py
pyosmo/end_conditions/endless.py
pyosmo/end_conditions/length.py
pyosmo/end_conditions/logical.py
pyosmo/end_conditions/step_coverage.py
pyosmo/end_conditions/time.py
pyosmo/error_strategy/__init__.py
pyosmo/error_strategy/allow_count.py
pyosmo/error_strategy/always_ignore.py
pyosmo/error_strategy/always_raise.py
pyosmo/error_strategy/base.py
pyosmo/error_strategy/ignore_asserts.py
pyosmo/history/__init__.py
pyosmo/history/history.py
pyosmo/history/statistics.py
pyosmo/history/test_case.py
pyosmo/history/test_step_log.py
pyosmo/models/__init__.py
pyosmo/models/osmo_model.py
pyosmo/models/random_delay_model.py
pyosmo/tests/__init__.py
pyosmo/tests/test_config.py
pyosmo/tests/test_core.py
pyosmo/tests/test_decorators.py
pyosmo/tests/test_end_conditions.py
pyosmo/tests/test_error_strategy.py
pyosmo/tests/test_fluent_config.py
pyosmo/tests/test_history_statistics.py
pyosmo/tests/algorithms/__init__.py
pyosmo/tests/algorithms/test_balancing_algo.py
pyosmo/tests/algorithms/test_weight_algo.py
pyosmo-0.2.2.dist-info/licenses/LICENSE
pyosmo-0.2.2.dist-info/METADATA
pyosmo-0.2.2.dist-info/WHEEL
pyosmo-0.2.2.dist-info/entry_points.txt
pyosmo-0.2.2.dist-info/top_level.txt
pyosmo-0.2.2.dist-info/RECORD
