Metadata-Version: 2.4
Name: pyosmo
Version: 0.2.2
Summary: pyosmo - a model-based testing tool
Author: Olli-Pekka Puolitaival
Author-email: Olli-Pekka Puolitaival <oopee1@gmail.com>
Maintainer: Olli-Pekka Puolitaival
Maintainer-email: Olli-Pekka Puolitaival <oopee1@gmail.com>
License: MIT
Classifier: Development Status :: 4 - Beta
Classifier: Intended Audience :: Developers
Classifier: License :: OSI Approved :: MIT License
Classifier: Programming Language :: Python :: 3
Classifier: Programming Language :: Python :: 3.11
Classifier: Programming Language :: Python :: 3.12
Classifier: Programming Language :: Python :: 3.13
Classifier: Programming Language :: Python :: 3.14
Requires-Python: >=3.11
License-File: LICENSE
Requires-Dist: click
Requires-Dist: mypy>=1.18.2
Requires-Dist: pytest>=9.0.0
Provides-Extra: dev
Requires-Dist: pytest>=7.0; extra == "dev"
Requires-Dist: hypothesis>=6.0; extra == "dev"
Requires-Dist: ruff>=0.1.0; extra == "dev"
Requires-Dist: mypy>=1.0; extra == "dev"
Dynamic: author
Dynamic: license-file
Dynamic: maintainer
Dynamic: requires-python
